dewmoth/VERSION
dewmoth/__init__.py
dewmoth/__main__.py
dewmoth/doccursor.py
dewmoth/docstring.py
dewmoth/parser.py
dewmoth/ext/__init__.py
dewmoth/ext/javadoc/__init__.py
dewmoth/ext/napoleon/__init__.py
dewmoth/ext/transformations/__init__.py
dewmoth/util/__init__.py
dewmoth/util/compiler.py
dewmoth/util/doccompat.py
dewmoth/util/readthedocs.py
dewmoth/util/strutil.py
dewmoth-0.19.0.dist-info/METADATA
dewmoth-0.19.0.dist-info/WHEEL
dewmoth-0.19.0.dist-info/entry_points.txt
dewmoth-0.19.0.dist-info/licenses/LICENSE
dewmoth-0.19.0.dist-info/RECORD
